evilafo-tools/__init__.py
evilafo-tools/bart_model.py
evilafo-tools/bert_model.py
evilafo-tools/utils.py
evilafo_tools/__init__.py
evilafo_tools/bart_model.py
evilafo_tools/bert_model.py
evilafo_tools-0.1.dist-info/licenses/LICENSE
evilafo_tools-0.1.dist-info/METADATA
evilafo_tools-0.1.dist-info/WHEEL
evilafo_tools-0.1.dist-info/top_level.txt
evilafo_tools-0.1.dist-info/RECORD
