Metadata-Version: 2.4
Name: evilafo-tools
Version: 0.1
Summary: A Python library for using BERT and BART
Home-page: https://github.com/Evilafo/Evilafo-tools
Author: Emmanuel Evilafo
Author-email: evil2846@gmail.com
Classifier: Programming Language :: Python :: 3
Classifier: License :: OSI Approved :: MIT License
Classifier: Operating System :: OS Independent
Requires-Python: >=3.6
License-File: LICENSE
Requires-Dist: transformers
Requires-Dist: torch
Requires-Dist: numpy
Dynamic: author
Dynamic: author-email
Dynamic: classifier
Dynamic: description
Dynamic: description-content-type
Dynamic: home-page
Dynamic: license-file
Dynamic: requires-dist
Dynamic: requires-python
Dynamic: summary
